bitdeer_ai/__about__.py
bitdeer_ai/__init__.py
bitdeer_ai/training/__init__.py
bitdeer_ai/training/client.py
bitdeer_ai/training/model.py
bitdeer_ai/training/resource_pb2.py
bitdeer_ai/training/training_pb2.py
bitdeer_ai/training/training_pb2_grpc.py
bitdeer_ai-0.0.4.dist-info/METADATA
bitdeer_ai-0.0.4.dist-info/WHEEL
bitdeer_ai-0.0.4.dist-info/licenses/LICENSE.txt
bitdeer_ai-0.0.4.dist-info/RECORD
